smi_python_tbi_parser/__init__.py
smi_python_tbi_parser/constants.py
smi_python_tbi_parser/project.py
smi_python_tbi_parser/tbi/__init__.py
smi_python_tbi_parser/tbi/changelog.py
smi_python_tbi_parser/tbi/external_process_engine.py
smi_python_tbi_parser/tbi/external_processing_engine_config.py
smi_python_tbi_parser/tbi/jenkins_pipeline.py
smi_python_tbi_parser/tbi/tbi.py
test/__init__.py
test/info/__init__.py
test/info/setmy/__init__.py
test/info/setmy/example/__init__.py
test/info/setmy/example/it_application.py
test/info/setmy/example/test_example.py
test/info/setmy/tbi/__init__.py
test/info/setmy/tbi/it_tbi.py
smi_python_tbi_parser-0.4.0.dist-info/LICENSE
smi_python_tbi_parser-0.4.0.dist-info/METADATA
smi_python_tbi_parser-0.4.0.dist-info/WHEEL
smi_python_tbi_parser-0.4.0.dist-info/top_level.txt
smi_python_tbi_parser-0.4.0.dist-info/RECORD
