Metadata-Version: 2.1
Name: smi-python-tbi-parser
Version: 0.4.0
Summary: setmy.info Python TBI parser library.
Home-page: https://github.com/setmy-info/python-tbi-parser
Author: Imre Tabur
Author-email: info@setmy.info
License: MIT
License-File: LICENSE
Requires-Dist: smi-python-commons ==0.3.3
